fishnet.py
fishnet-1.18.2.dist-info/LICENSE.txt
fishnet-1.18.2.dist-info/METADATA
fishnet-1.18.2.dist-info/WHEEL
fishnet-1.18.2.dist-info/top_level.txt
fishnet-1.18.2.dist-info/RECORD
