Metadata-Version: 2.1
Name: fishnet
Version: 1.18.2
Summary: Distributed Stockfish analysis for lichess.org
Home-page: https://github.com/niklasf/fishnet
Author: Niklas Fiekas
Author-email: niklas.fiekas@backscattering.de
License: UNKNOWN
Keywords: lichess.org lichess chess stockfish uci
Platform: UNKNOWN
Classifier: Development Status :: 7 - Inactive
Classifier: Environment :: Console
Classifier: Intended Audience :: Developers
Classifier: Intended Audience :: End Users/Desktop
Classifier: License :: OSI Approved :: GNU General Public License v3 or later (GPLv3+)
Classifier: Operating System :: OS Independent
Classifier: Programming Language :: Python
Classifier: Programming Language :: Python :: 2
Classifier: Programming Language :: Python :: 2.7
Classifier: Programming Language :: Python :: 3
Classifier: Programming Language :: Python :: 3.4
Classifier: Programming Language :: Python :: 3.5
Classifier: Programming Language :: Python :: 3.6
Classifier: Programming Language :: Python :: 3.7
Classifier: Programming Language :: Python :: 3.8
Classifier: Programming Language :: Python :: 3.9
Classifier: Topic :: Games/Entertainment :: Board Games
Classifier: Topic :: Internet :: WWW/HTTP
Requires-Python: >=2.7,!=3.0.*,!=3.1.*,!=3.2.*
Requires-Dist: requests (<3,>=2)
